conda_build_demo/__init__.py
conda_build_demo/demo.py
conda_build_demo-0.0.3.dist-info/licenses/LICENSE
conda_build_demo-0.0.3.dist-info/METADATA
conda_build_demo-0.0.3.dist-info/WHEEL
conda_build_demo-0.0.3.dist-info/top_level.txt
conda_build_demo-0.0.3.dist-info/RECORD
