Metadata-Version: 2.4
Name: conda-build-demo
Version: 0.0.3
Summary: A make-believe Python project for illustrating Conda packaging
Author-email: Joseph Lamoree <joseph@lamoree.com>
License: MIT
Project-URL: Homepage, https://codeberg.org/jlamoree/conda-build-demo
Keywords: conda,demo
Classifier: Programming Language :: Python :: 3
Classifier: License :: OSI Approved :: MIT License
Classifier: Operating System :: OS Independent
Requires-Python: >=3.10
License-File: LICENSE
Dynamic: license-file
